linkmailLensApi/__init__.py
linkmailLensApi/linkmailLensApi.py
linkmailLensApi-1.1.dist-info/LICENSE
linkmailLensApi-1.1.dist-info/METADATA
linkmailLensApi-1.1.dist-info/WHEEL
linkmailLensApi-1.1.dist-info/top_level.txt
linkmailLensApi-1.1.dist-info/RECORD
