Metadata-Version: 2.1
Name: linkmailLensApi
Version: 1.1
Summary: Api no oficial de Google lens creada por mi.
Home-page: https://github.com/Linkmail16/linkmailLensApi
Download-URL: https://github.com/Linkmail16/linkmailLensApi/archive/refs/tags/v0.3.tar.gz
Author: Linkmail
Author-email: 
Keywords: api,google,google lens
Classifier: Programming Language :: Python :: 3
Classifier: License :: OSI Approved :: MIT License
Classifier: Operating System :: OS Independent
Requires-Python: >=3.6
License-File: LICENSE
Requires-Dist: requests
Requires-Dist: beautifulsoup4
Requires-Dist: pillow
